uqrng_direct/.gitlab-ci.yml
uqrng_direct/__init__.py
uqrng_direct/client.py
uqrng_direct/uqrng_pb2.py
uqrng_direct/uqrng_pb2_grpc.py
uqrng_direct/uqrng_server_sim.py
uqrng_direct/utils.py
uqrng_direct-1.0.0.dist-info/METADATA
uqrng_direct-1.0.0.dist-info/WHEEL
uqrng_direct-1.0.0.dist-info/top_level.txt
uqrng_direct-1.0.0.dist-info/RECORD
