Metadata-Version: 2.1
Name: uqrng_direct
Version: 1.0.0
Summary: Client interface for QCi's uniform quantum random number generator (uQRNG) device.
Author: Quantum Computing Inc.
Author-email: support@quantumcomputinginc.com
Maintainer: David Haycraft
Maintainer-email: dhaycraft@quantumcomputinginc.com
License: Apache 2.0
Requires-Python: >=3.8
Requires-Dist: grpcio-tools ==1.47.0
Requires-Dist: protobuf ==3.20.3
Requires-Dist: numpy <2,>=1.24.1
Provides-Extra: dev
Requires-Dist: black <23,>=22.6.0 ; extra == 'dev'
Requires-Dist: build <0.11.0,>=0.10.0 ; extra == 'dev'
Requires-Dist: check-manifest <0.49,>=0.48 ; extra == 'dev'
Requires-Dist: coverage[toml] <7,>=6.4.2 ; extra == 'dev'
Requires-Dist: pylint <3,>=2.14.0 ; extra == 'dev'
Requires-Dist: pytest <8,>=7.1.0 ; extra == 'dev'
Requires-Dist: sphinx-rtd-theme >=1.3.0 ; extra == 'dev'
